LICENSE
README.md
__init__.py
main.py
setup.py
primitives/__init__.py
primitives/prompts/__init__.py
primitives/prompts/common_workflows.py
primitives/resources/__init__.py
primitives/resources/data_dragon_resources.py
primitives/resources/game_constants_resources.py
primitives/tools/__init__.py
primitives/tools/account_tools.py
primitives/tools/challenges_tools.py
primitives/tools/champion_tools.py
primitives/tools/clash_tools.py
primitives/tools/league_tools.py
primitives/tools/match_tools.py
primitives/tools/spectator_tools.py
primitives/tools/status_tools.py
primitives/tools/summoner_tools.py
primitives/tools/tournament_tools.py
services/__init__.py
services/riot_api_service.py
utils/__init__.py
utils/formatters.py
league_mcp_server-0.1.0.dist-info/METADATA
league_mcp_server-0.1.0.dist-info/WHEEL
league_mcp_server-0.1.0.dist-info/entry_points.txt
league_mcp_server-0.1.0.dist-info/licenses/LICENSE
league_mcp_server-0.1.0.dist-info/RECORD
