Metadata-Version: 2.4
Name: league-mcp-server
Version: 0.1.0
Summary: Model Context Protocol server for League of Legends game data via Riot Games API
Project-URL: Homepage, https://github.com/your-username/League-MCP
Project-URL: Repository, https://github.com/your-username/League-MCP
Project-URL: Documentation, https://github.com/your-username/League-MCP/blob/main/README.md
Project-URL: Issues, https://github.com/your-username/League-MCP/issues
Author: League MCP Contributors
License: MIT License
License-File: LICENSE
Keywords: api,gaming,league-of-legends,mcp,model-context-protocol,riot-games
Classifier: Development Status :: 4 - Beta
Classifier: Intended Audience :: Developers
Classifier: License :: OSI Approved :: MIT License
Classifier: Programming Language :: Python :: 3
Classifier: Programming Language :: Python :: 3.12
Classifier: Topic :: Games/Entertainment
Classifier: Topic :: Software Development :: Libraries :: Python Modules
Requires-Python: >=3.12
Requires-Dist: httpx>=0.28.1
Requires-Dist: mcp[cli]>=1.9.4
Requires-Dist: python-dotenv>=1.1.0
Requires-Dist: requests>=2.31.0
Provides-Extra: dev
Requires-Dist: black>=23.0.0; extra == 'dev'
Requires-Dist: isort>=5.12.0; extra == 'dev'
Requires-Dist: mypy>=1.5.0; extra == 'dev'
Requires-Dist: pytest-asyncio>=0.21.0; extra == 'dev'
Requires-Dist: pytest>=7.0.0; extra == 'dev'
